PyMoCapViewer/__init__.py
PyMoCapViewer/mocap_viewer.py
PyMoCapViewer/utils.py
PyMoCapViewer/examples/__init__.py
PyMoCapViewer/examples/downloader.py
PyMoCapViewer/skeletons/__init__.py
PyMoCapViewer/skeletons/azure_kinect.py
PyMoCapViewer/skeletons/ghum.py
PyMoCapViewer/skeletons/h36m.py
PyMoCapViewer/skeletons/kinect_v2.py
PyMoCapViewer/skeletons/skeleton_loader.py
PyMoCapViewer/skeletons/vicon_plug_in_gait.py
PyMoCapViewer/skeletons/vnect.py
PyMoCapViewer-0.0.15.dist-info/LICENSE
PyMoCapViewer-0.0.15.dist-info/METADATA
PyMoCapViewer-0.0.15.dist-info/WHEEL
PyMoCapViewer-0.0.15.dist-info/top_level.txt
PyMoCapViewer-0.0.15.dist-info/RECORD
