Metadata-Version: 2.1
Name: PyMoCapViewer
Version: 0.0.15
Summary: A once-simple 3D motion capture visualizer that is becoming more advanced over time.
Author-email: Justin Amadeus Albert <justin_albert@gmx.de>
Project-URL: Homepage, https://github.com/justamad/PyMoCapViewer
Project-URL: Issues, https://github.com/justamad/PyMoCapViewer
Classifier: Programming Language :: Python :: 3
Classifier: License :: OSI Approved :: MIT License
Classifier: Operating System :: OS Independent
Requires-Python: >=3.8
License-File: LICENSE
Requires-Dist: vtk ==9.3.1
Requires-Dist: open3d ==0.18.0
Requires-Dist: numpy ==2.0.1
Requires-Dist: pandas ==2.2.2
Requires-Dist: scipy ==1.14.0
